express_relay/__init__.py
express_relay/client.py
express_relay/constants.py
express_relay/idl/idlExpressRelay.json
express_relay/models/__init__.py
express_relay/models/base.py
express_relay/models/svm.py
express_relay/searcher/examples/simple_searcher_svm.py
express_relay/searcher/examples/testing_searcher_svm.py
express_relay/svm/__init__.py
express_relay/svm/generated/__init__.py
express_relay/svm/generated/express_relay/__init__.py
express_relay/svm/generated/express_relay/accounts/__init__.py
express_relay/svm/generated/express_relay/accounts/config_router.py
express_relay/svm/generated/express_relay/accounts/express_relay_metadata.py
express_relay/svm/generated/express_relay/errors/__init__.py
express_relay/svm/generated/express_relay/errors/anchor.py
express_relay/svm/generated/express_relay/errors/custom.py
express_relay/svm/generated/express_relay/instructions/__init__.py
express_relay/svm/generated/express_relay/instructions/check_permission.py
express_relay/svm/generated/express_relay/instructions/initialize.py
express_relay/svm/generated/express_relay/instructions/set_admin.py
express_relay/svm/generated/express_relay/instructions/set_relayer.py
express_relay/svm/generated/express_relay/instructions/set_router_split.py
express_relay/svm/generated/express_relay/instructions/set_secondary_relayer.py
express_relay/svm/generated/express_relay/instructions/set_splits.py
express_relay/svm/generated/express_relay/instructions/set_swap_platform_fee.py
express_relay/svm/generated/express_relay/instructions/submit_bid.py
express_relay/svm/generated/express_relay/instructions/swap.py
express_relay/svm/generated/express_relay/instructions/swap_internal.py
express_relay/svm/generated/express_relay/instructions/swap_v2.py
express_relay/svm/generated/express_relay/instructions/withdraw_fees.py
express_relay/svm/generated/express_relay/program_id.py
express_relay/svm/generated/express_relay/types/__init__.py
express_relay/svm/generated/express_relay/types/fee_token.py
express_relay-0.28.0.dist-info/METADATA
express_relay-0.28.0.dist-info/WHEEL
express_relay-0.28.0.dist-info/RECORD
