Metadata-Version: 2.3
Name: express-relay
Version: 0.28.0
Summary: Utilities for searchers and protocols to interact with the Express Relay protocol.
License: Apache-2.0
Author: dourolabs
Requires-Python: >=3.11,<4.0
Classifier: License :: OSI Approved :: Apache Software License
Classifier: Programming Language :: Python :: 3
Classifier: Programming Language :: Python :: 3.11
Classifier: Programming Language :: Python :: 3.12
Classifier: Programming Language :: Python :: 3.13
Requires-Dist: anchorpy (>=0.21.0,<0.22.0)
Requires-Dist: argparse (>=1.4.0,<2.0.0)
Requires-Dist: httpx (>=0.28.1,<0.29.0)
Requires-Dist: pydantic (>=2.10.6,<3.0.0)
Requires-Dist: solana (>=0.36.6,<0.37.0)
Requires-Dist: web3 (>=7.8.0,<8.0.0)
Requires-Dist: websockets (>=10.0,<11.0)
